drf_paytm/__init__.py
drf_paytm/admin.py
drf_paytm/apps.py
drf_paytm/models.py
drf_paytm/paytmapi.py
drf_paytm/serializers.py
drf_paytm/tests.py
drf_paytm/urls.py
drf_paytm/utils.py
drf_paytm/variables.py
drf_paytm/views.py
drf_paytm/migrations/0001_initial.py
drf_paytm/migrations/0002_auto_20190613_1613.py
drf_paytm/migrations/__init__.py
drf_paytm/signals/__init__.py
drf_paytm/signals/handlers.py
drf_paytm-0.0.3.dist-info/LICENSE
drf_paytm-0.0.3.dist-info/METADATA
drf_paytm-0.0.3.dist-info/WHEEL
drf_paytm-0.0.3.dist-info/top_level.txt
drf_paytm-0.0.3.dist-info/RECORD
