Metadata-Version: 2.1
Name: drf-paytm
Version: 0.0.3
Summary: PayTM Integration based on Django REST Framework
Home-page: https://github.com/101Loop/drf_paytm
Author: 101Loop
Author-email: pypidev@civilmachines.com
License: GPLv3
Platform: UNKNOWN
Classifier: Development Status :: 5 - Production/Stable
Classifier: Environment :: Web Environment
Classifier: Framework :: Django
Classifier: Framework :: Django :: 1.11
Classifier: Framework :: Django :: 2.0
Classifier: Framework :: Django :: 2.1
Classifier: Intended Audience :: Developers
Classifier: License :: OSI Approved :: GNU General Public License v3 (GPLv3)
Classifier: Operating System :: OS Independent
Classifier: Programming Language :: Python
Classifier: Programming Language :: Python :: 3
Classifier: Programming Language :: Python :: 3.4
Classifier: Programming Language :: Python :: 3.5
Classifier: Programming Language :: Python :: 3.6
Classifier: Programming Language :: Python :: 3.7
Classifier: Topic :: Internet :: WWW/HTTP
Requires-Python: >=3.4
Requires-Dist: Django (>=1.11)
Requires-Dist: djangorestframework (>=3.9.0)
Requires-Dist: drfaddons (>=0.1.0)
Requires-Dist: requests (>=2.21.0)
Requires-Dist: pycrypto (>=2.6.1)
